[
  {
    "anonymous": false,
    "inputs": [
      {
        "indexed": true,
        "internalType": "address",
        "name": "organizer",
        "type": "address"
      },
      {
        "indexed": true,
        "internalType": "uint256",
        "name": "prizeId",
        "type": "uint256"
      },
      {
        "indexed": false,
        "internalType": "string",
        "name": "name",
        "type": "string"
      },
      {
        "indexed": false,
        "internalType": "uint256",
        "name": "pool",
        "type": "uint256"
      }
    ],
    "name": "PrizeCreated",
    "type": "event"
  },
  {
    "anonymous": false,
    "inputs": [
      {
        "indexed": true,
        "internalType": "uint256",
        "name": "prizeId",
        "type": "uint256"
      },
      {
        "indexed": true,
        "internalType": "address",
        "name": "organizer",
        "type": "address"
      }
    ],
    "name": "PrizeOrganizerSet",
    "type": "event"
  },
  {
    "inputs": [
      {
        "components": [
          {
            "internalType": "string",
            "name": "name",
            "type": "string"
          },
          {
            "internalType": "string",
            "name": "description",
            "type": "string"
          },
          {
            "internalType": "uint256",
            "name": "pool",
            "type": "uint256"
          },
          {
            "internalType": "string[]",
            "name": "criteria",
            "type": "string[]"
          },
          {
            "internalType": "uint32[]",
            "name": "criteriaWeights",
            "type": "uint32[]"
          }
        ],
        "internalType": "struct PrizeManagerFacet.PrizeParams",
        "name": "params",
        "type": "tuple"
      }
    ],
    "name": "createPrize",
    "outputs": [
      {
        "internalType": "uint256",
        "name": "",
        "type": "uint256"
      }
    ],
    "stateMutability": "nonpayable",
    "type": "function"
  },
  {
    "inputs": [],
    "name": "getPrizeCount",
    "outputs": [
      {
        "internalType": "uint256",
        "name": "",
        "type": "uint256"
      }
    ],
    "stateMutability": "view",
    "type": "function"
  },
  {
    "inputs": [
      {
        "internalType": "uint256",
        "name": "prizeId",
        "type": "uint256"
      }
    ],
    "name": "getPrizeDetails",
    "outputs": [
      {
        "components": [
          {
            "internalType": "uint256",
            "name": "id",
            "type": "uint256"
          },
          {
            "internalType": "address",
            "name": "organizer",
            "type": "address"
          },
          {
            "internalType": "string",
            "name": "name",
            "type": "string"
          },
          {
            "internalType": "string",
            "name": "description",
            "type": "string"
          },
          {
            "internalType": "uint256",
            "name": "monetaryRewardPool",
            "type": "uint256"
          },
          {
            "internalType": "enum LibPrize.State",
            "name": "state",
            "type": "uint8"
          },
          {
            "internalType": "string[]",
            "name": "criteriaNames",
            "type": "string[]"
          },
          {
            "internalType": "uint32[]",
            "name": "criteriaWeights",
            "type": "uint32[]"
          },
          {
            "internalType": "uint256",
            "name": "createdAt",
            "type": "uint256"
          },
          {
            "internalType": "contract IAllocationStrategy",
            "name": "strategy",
            "type": "address"
          },
          {
            "internalType": "uint256",
            "name": "contributionCount",
            "type": "uint256"
          }
        ],
        "internalType": "struct PrizeManagerFacet.PrizeDetails",
        "name": "",
        "type": "tuple"
      }
    ],
    "stateMutability": "view",
    "type": "function"
  },
  {
    "inputs": [],
    "name": "getPrizes",
    "outputs": [
      {
        "components": [
          {
            "internalType": "uint256",
            "name": "id",
            "type": "uint256"
          },
          {
            "internalType": "address",
            "name": "organizer",
            "type": "address"
          },
          {
            "internalType": "string",
            "name": "name",
            "type": "string"
          },
          {
            "internalType": "string",
            "name": "description",
            "type": "string"
          },
          {
            "internalType": "uint256",
            "name": "monetaryRewardPool",
            "type": "uint256"
          },
          {
            "internalType": "enum LibPrize.State",
            "name": "state",
            "type": "uint8"
          },
          {
            "internalType": "string[]",
            "name": "criteriaNames",
            "type": "string[]"
          },
          {
            "internalType": "uint32[]",
            "name": "criteriaWeights",
            "type": "uint32[]"
          },
          {
            "internalType": "uint256",
            "name": "createdAt",
            "type": "uint256"
          },
          {
            "internalType": "contract IAllocationStrategy",
            "name": "strategy",
            "type": "address"
          },
          {
            "internalType": "uint256",
            "name": "contributionCount",
            "type": "uint256"
          }
        ],
        "internalType": "struct PrizeManagerFacet.PrizeDetails[]",
        "name": "",
        "type": "tuple[]"
      }
    ],
    "stateMutability": "view",
    "type": "function"
  }
]